RAISE/Quantas2rMATS.py
RAISE/__init__.py
RAISE/calculate_activity.py
RAISE/cli.py
RAISE/construct_network.py
RAISE/find_target.py
RAISE/plot_target.py
raise_rbp-0.1.4.dist-info/licenses/LICENSE
raise_rbp-0.1.4.dist-info/METADATA
raise_rbp-0.1.4.dist-info/WHEEL
raise_rbp-0.1.4.dist-info/top_level.txt
raise_rbp-0.1.4.dist-info/RECORD
