Metadata-Version: 2.4
Name: RAISE-RBP
Version: 0.1.4
Summary: RBP Activity Inference from Splicing Events
Author-email: liuyilei8969 <ylliu8969@gmail.com>
License: GNU General Public License v3 (GPLv3)
Project-URL: Homepage, https://github.com/liuyilei8969/RAISE/
Project-URL: Issues, https://github.com/liuyilei8969/RAISE/issues
Classifier: Programming Language :: Python :: 3
Classifier: Operating System :: OS Independent
Classifier: License :: OSI Approved :: GNU General Public License v3 (GPLv3)
Requires-Python: >=3.8
License-File: LICENSE
Requires-Dist: pandas
Requires-Dist: numpy
Requires-Dist: networkx
Requires-Dist: scikit-learn
Requires-Dist: argparse
Requires-Dist: Bio
Requires-Dist: pybedtools
Dynamic: license-file
